jsonrefiner/__init__.py
jsonrefiner-0.1.2.dist-info/METADATA
jsonrefiner-0.1.2.dist-info/WHEEL
jsonrefiner-0.1.2.dist-info/RECORD
